modal_2fa/__init__.py
modal_2fa/admin.py
modal_2fa/admin_apps.py
modal_2fa/admin_site.py
modal_2fa/apps.py
modal_2fa/auth.py
modal_2fa/backends.py
modal_2fa/customise.py
modal_2fa/forms.py
modal_2fa/menus.py
modal_2fa/models.py
modal_2fa/settings_helper.py
modal_2fa/urls.py
modal_2fa/user_admin.py
modal_2fa/users.py
modal_2fa/utils.py
modal_2fa/webauthn.py
modal_2fa/management/__init__.py
modal_2fa/management/commands/__init__.py
modal_2fa/management/commands/clear_failed_logins.py
modal_2fa/migrations/0001_initial.py
modal_2fa/migrations/0002_failedloginattempt_webauthncredential.py
modal_2fa/migrations/0003_webauthncredential_rp_id.py
modal_2fa/migrations/__init__.py
modal_2fa/static/modal_2fa/webauthn.js
modal_2fa/templates/modal_2fa/base.html
modal_2fa/templates/modal_2fa/database_cookies.html
modal_2fa/templates/modal_2fa/new_totp.html
modal_2fa/templates/modal_2fa/user_admin_modal.html
modal_2fa/templates/modal_2fa/webauthn_devices.html
modal_2fa/templates/modal_2fa/emails/invite.html
modal_2fa/templates/modal_2fa/emails/invite_subject.txt
modal_2fa/templates/modal_2fa/emails/invite_txt.html
modal_2fa/templates/modal_2fa/emails/password_reset_email.html
modal_2fa/templates/modal_2fa/emails/password_reset_subject.txt
django_modal_2fa-0.0.5.dist-info/LICENSE
django_modal_2fa-0.0.5.dist-info/METADATA
django_modal_2fa-0.0.5.dist-info/WHEEL
django_modal_2fa-0.0.5.dist-info/top_level.txt
django_modal_2fa-0.0.5.dist-info/RECORD
