Metadata-Version: 2.1
Name: django-modal-2fa
Version: 0.0.5
Summary: Django app to implement two factor authentication with bootstrap modals
Home-page: https://github.com/jonesim/django-2fa
Author: Ian Jones
Classifier: Programming Language :: Python :: 3
Classifier: License :: OSI Approved :: MIT License
Classifier: Operating System :: OS Independent
Requires-Python: >=3.6
License-File: LICENSE
Requires-Dist: django-nested-modals
Requires-Dist: qrcode
Requires-Dist: django-otp
Requires-Dist: webauthn >=2.0.0
